{
  "project_info": {
    "project_number": "362380349341",
    "project_id": "snapcensus",
    "storage_bucket": "snapcensus.appspot.com"
  },
  "client": [
    {
      "client_info": {
        "mobilesdk_app_id": "1:362380349341:android:9332503b1452bf71662974",
        "android_client_info": {
          "package_name": "com.example.snapcensus"
        }
      },
      "oauth_client": [],
      "api_key": [
        {
          "current_key": "AIzaSyAE6fmmY4NrimEM2oZdhOAWuCNhgJfMshs"
        }
      ],
      "services": {
        "appinvite_service": {
          "other_platform_oauth_client": []
        }
      }
    }
  ],
  "configuration_version": "1"
}